{"katie": {"email": "katie@.com", "username": "katie", "mast_password": "$2b$12$w9lQDkGjx.Rc/y6igEZl1OLUeHVM.uf5VlWM.AW5EY84RvzBBv5qW", "entries": {"kite.com": {"url": "kite.com", "email": "katie@.com", "password": "gAAAAABjjBCwHnLOd8-Ky9f9VWr0-xfLD4e5qBohC4pnwlTuDMPUhEnfjPSZKu8NIDUVTXR8mkeOAYlvQIvR3OI_Z116oProBQ==", "username": ""}}}, "leonie": {"email": "leon!.com", "username": "leonie", "mast_password": "$2b$12$Vbm37C7NNa/3yRRoL5evl.eHsMXbi5lLytLr7jtC/sfpstLIQP.B.", "entries": {}}, "mikee": {"email": "mike@.com", "username": "mikee", "mast_password": "$2b$12$L1/Y4W41dD3tUSla1j0LduCF/YUJXw3qdCnwUxQCzN7Cg9rR0M/US", "entries": {"hertz.com": {"url": "hertz.com", "email": "mike@.com", "password": "gAAAAABjjV4GEhON7eOC_cFMVkUfvkzm9gLqi36AhdjwUk4tnBNB0b2QIYj03EnTDOr5sR7YH8yA4Pi0xixOLOYtA-9tlGmP6g==", "username": ""}}}, "MikeeBoy": {"email": "mike@.com", "username": "MikeeBoy", "mast_password": "$2b$12$ACCQu5D7R9Sz1fGB67VH5uHZr7qLnd1MNEdW7VonbbszLFes7tMme", "entries": {}}, "garry": {"email": "garry@.com", "username": "garry", "mast_password": "$2b$12$Zae8xc9EKArouSOd49GlmuI3mv1YyYS4HshtSoJE3siTjFDGjfcDa", "entries": {}}, "frank": {"email": "frankieboy@gmail.com", "username": "frank", "mast_password": "Password", "entries": {}}, "PeterDude": {"email": "peter@gmail.com", "username": "PeterDude", "mast_password": "$2b$12$/S8EjPgHRr4QxI8i2eXW1.e4qyPJ0crK2BfiE0ZNj/L1ah6roYrzi", "entries": {"ghosts.com.au": {"url": "ghosts.com.au", "email": "peter@gmail.com", "password": "gAAAAABjmruB7FuqOUmbiSws3GjnvUJdJnck2y9hMEnrIWdWiRCDhAEQtrK1bwMtjhzmvS17ihP8Fcc1THA4wNQmZ3oZP9l5jg==", "username": "PeterDude"}}}}